<?xml version="1.0" encoding="utf-8"?><HelpTOCNode Title="IMyControl Methods" Url="html/3300EADC.htm"><HelpTOCNode Title="GetAnalogState Method " Url="html/FD010D79.htm" /><HelpTOCNode Title="GetControlButtonName Method " Url="html/3E475310.htm" /><HelpTOCNode Title="GetControlDescription Method " Url="html/48ADAEBB.htm" /><HelpTOCNode Title="GetControlName Method " Url="html/CCDFD9BE.htm" /><HelpTOCNode Title="GetControlTypeEnum Method " Url="html/6FC970FC.htm" /><HelpTOCNode Title="GetGameControlEnum Method " Url="html/5DF55B89.htm" /><HelpTOCNode Title="GetKeyboardControl Method " Url="html/96648EE9.htm" /><HelpTOCNode Title="GetMouseControl Method " Url="html/D9A646F5.htm" /><HelpTOCNode Title="GetSecondKeyboardControl Method " Url="html/AC1283AC.htm" /><HelpTOCNode Title="IsControlAssigned Method " Url="html/A9582637.htm" /><HelpTOCNode Title="IsJoystickPressed Method " Url="html/A2E09E69.htm" /><HelpTOCNode Title="IsNewJoystickPressed Method " Url="html/89D4633F.htm" /><HelpTOCNode Title="IsNewJoystickReleased Method " Url="html/16D1DF73.htm" /><HelpTOCNode Title="IsNewPressed Method " Url="html/16952717.htm" /><HelpTOCNode Title="IsNewReleased Method " Url="html/BAF34447.htm" /><HelpTOCNode Title="IsPressed Method " Url="html/9853B20D.htm" /></HelpTOCNode>